earth_data_fetcher/__init__.py
earth_data_fetcher/download_dataset.py
earth_data_fetcher/download_https.py
earth_data_fetcher/utils.py
earth_data_fetcher-0.1.2.dist-info/METADATA
earth_data_fetcher-0.1.2.dist-info/WHEEL
earth_data_fetcher-0.1.2.dist-info/top_level.txt
earth_data_fetcher-0.1.2.dist-info/RECORD
