Metadata-Version: 2.2
Name: earth-data-fetcher
Version: 0.1.2
Summary: Fetch remote sensing and reanalysis data from different sources
Requires-Python: >=3.10
Requires-Dist: aiohttp>=3.10
Requires-Dist: copernicusmarine>=2.0.0
Requires-Dist: fsspec>=2024
Requires-Dist: jinja2>=3
Requires-Dist: loguru>=0.7
Requires-Dist: munch>=3
Requires-Dist: pip>=23
Requires-Dist: pydap>=3.3
Requires-Dist: python-dotenv>=1.0
Requires-Dist: requests>=2
Requires-Dist: s3fs>=2024
